setup.py
disenchained/__init__.py
disenchained/decorators.py
disenchained/panels.py
disenchained/query.py
django_disenchained.egg-info/PKG-INFO
django_disenchained.egg-info/SOURCES.txt
django_disenchained.egg-info/dependency_links.txt
django_disenchained.egg-info/requires.txt
django_disenchained.egg-info/top_level.txt