Metadata-Version: 1.1
Name: django-disenchained
Version: 0.8
Summary: django-disenchained: free Django from the shackles of inefficient queries!
Home-page: http://github.com/abhik/django-disenchained
Author: Abhik Shah
Author-email: abhik@counsyl.com
License: BSD
Platform: UNKNOWN
Classifier: Development Status :: 4 - Beta
Classifier: Environment :: Web Environment
Classifier: Framework :: Django
Classifier: Intended Audience :: Developers
Classifier: License :: OSI Approved :: BSD License
Classifier: Operating System :: OS Independent
Classifier: Programming Language :: Python
Classifier: Topic :: Software Development :: Libraries :: Python Modules
